mkdocs_puml_mod/__init__.py
mkdocs_puml_mod/encoder.py
mkdocs_puml_mod/fence.py
mkdocs_puml_mod/plugin.py
mkdocs_puml_mod/puml.py
mkdocs_puml_mod-1.2.0.dist-info/entry_points.txt
mkdocs_puml_mod-1.2.0.dist-info/LICENSE
mkdocs_puml_mod-1.2.0.dist-info/WHEEL
mkdocs_puml_mod-1.2.0.dist-info/METADATA
mkdocs_puml_mod-1.2.0.dist-info/RECORD
