Metadata-Version: 2.1
Name: mkdocs-puml-mod
Version: 1.2.0
Summary: Package that brings PlantUML to MkDocs
Author-email: "Mikhail Kravets, Saurabh Rajguru" <michkravets@gmail.com>
Requires-Python: >=3.8
Classifier: License :: OSI Approved :: MIT License
Requires-Dist: requests >= 2.27, < 3.0
Requires-Dist: markdown >= 3.2.1, < 4.0
Requires-Dist: mkdocs >= 1.3, < 2.0
Project-URL: Home, https://github.com/rajguru7/mkdocs-puml-mod
